{
  "generatedAt": "2026-05-28T14:02:47.774Z",
  "capacity": 20011,
  "loadFactors": [
    0.1,
    0.25,
    0.5,
    0.7,
    0.8,
    0.9
  ],
  "runs": 3,
  "results": [
    {
      "table": "Separate Chaining",
      "loadFactor": 0.1,
      "capacity": 20011,
      "itemCount": 2001,
      "searchCount": 4002,
      "insertMedianMs": 3.60990000000038,
      "insertRunsMs": [
        3.60990000000038,
        4.701399999999921,
        1.5856999999996333
      ],
      "insertUsPerOp": 1.804047976012184,
      "searchMedianMs": 0.7975999999998749,
      "searchRunsMs": [
        1.594600000000355,
        0.7901000000001659,
        0.7975999999998749
      ],
      "searchUsPerOp": 0.19930034982505618,
      "found": 2001
    },
    {
      "table": "Linear Probing",
      "loadFactor": 0.1,
      "capacity": 20011,
      "itemCount": 2001,
      "searchCount": 4002,
      "insertMedianMs": 0.7339000000001761,
      "insertRunsMs": [
        0.907799999999952,
        0.7339000000001761,
        0.572400000000016
      ],
      "insertUsPerOp": 0.36676661669174215,
      "searchMedianMs": 1.155999999999949,
      "searchRunsMs": [
        1.5364999999992506,
        1.155999999999949,
        0.6526000000003478
      ],
      "searchUsPerOp": 0.2888555722138803,
      "found": 2001
    },
    {
      "table": "Double Hashing",
      "loadFactor": 0.1,
      "capacity": 20011,
      "itemCount": 2001,
      "searchCount": 4002,
      "insertMedianMs": 0.7866999999996551,
      "insertRunsMs": [
        2.7968000000000757,
        0.7866999999996551,
        0.6683999999995649
      ],
      "insertUsPerOp": 0.3931534232881835,
      "searchMedianMs": 1.2532000000001062,
      "searchRunsMs": [
        1.2532000000001062,
        1.0995999999995547,
        1.7439999999996871
      ],
      "searchUsPerOp": 0.3131434282858836,
      "found": 2001
    },
    {
      "table": "Separate Chaining",
      "loadFactor": 0.25,
      "capacity": 20011,
      "itemCount": 5002,
      "searchCount": 10004,
      "insertMedianMs": 2.157600000000457,
      "insertRunsMs": [
        3.804200000000492,
        2.157600000000457,
        2.148699999999735
      ],
      "insertUsPerOp": 0.4313474610156851,
      "searchMedianMs": 1.9084000000002561,
      "searchRunsMs": [
        2.115899999999783,
        1.9084000000002561,
        1.610700000000179
      ],
      "searchUsPerOp": 0.19076369452221673,
      "found": 5002
    },
    {
      "table": "Linear Probing",
      "loadFactor": 0.25,
      "capacity": 20011,
      "itemCount": 5002,
      "searchCount": 10004,
      "insertMedianMs": 1.0430999999998676,
      "insertRunsMs": [
        1.0430999999998676,
        6.137199999999211,
        0.8249000000005253
      ],
      "insertUsPerOp": 0.2085365853658272,
      "searchMedianMs": 1.5156000000006316,
      "searchRunsMs": [
        1.5423000000000684,
        1.5156000000006316,
        1.5034000000005108
      ],
      "searchUsPerOp": 0.15149940023996716,
      "found": 5002
    },
    {
      "table": "Double Hashing",
      "loadFactor": 0.25,
      "capacity": 20011,
      "itemCount": 5002,
      "searchCount": 10004,
      "insertMedianMs": 1.253700000000208,
      "insertRunsMs": [
        1.3821000000007189,
        1.253700000000208,
        1.0787000000000262
      ],
      "insertUsPerOp": 0.25063974410240064,
      "searchMedianMs": 2.0367000000005646,
      "searchRunsMs": [
        2.0918000000001484,
        2.0367000000005646,
        2.0324000000000524
      ],
      "searchUsPerOp": 0.20358856457422678,
      "found": 5002
    },
    {
      "table": "Separate Chaining",
      "loadFactor": 0.5,
      "capacity": 20011,
      "itemCount": 10005,
      "searchCount": 20010,
      "insertMedianMs": 3.8807000000006155,
      "insertRunsMs": [
        3.8807000000006155,
        3.2401999999992768,
        6.757599999999911
      ],
      "insertUsPerOp": 0.38787606196907704,
      "searchMedianMs": 3.0652000000000044,
      "searchRunsMs": [
        3.7638999999999214,
        3.0652000000000044,
        3.0083000000004176
      ],
      "searchUsPerOp": 0.15318340829585228,
      "found": 10005
    },
    {
      "table": "Linear Probing",
      "loadFactor": 0.5,
      "capacity": 20011,
      "itemCount": 10005,
      "searchCount": 20010,
      "insertMedianMs": 1.5018999999992957,
      "insertRunsMs": [
        1.5057999999999083,
        1.4627000000000407,
        1.5018999999992957
      ],
      "insertUsPerOp": 0.15011494252866522,
      "searchMedianMs": 3.2942000000002736,
      "searchRunsMs": [
        3.283300000000054,
        3.3380999999999403,
        3.2942000000002736
      ],
      "searchUsPerOp": 0.1646276861569352,
      "found": 10005
    },
    {
      "table": "Double Hashing",
      "loadFactor": 0.5,
      "capacity": 20011,
      "itemCount": 10005,
      "searchCount": 20010,
      "insertMedianMs": 2.0808999999999287,
      "insertRunsMs": [
        2.06670000000031,
        2.119800000000396,
        2.0808999999999287
      ],
      "insertUsPerOp": 0.2079860069964946,
      "searchMedianMs": 4.5659999999998035,
      "searchRunsMs": [
        4.610999999999876,
        4.5659999999998035,
        4.530000000000655
      ],
      "searchUsPerOp": 0.22818590704646693,
      "found": 10005
    },
    {
      "table": "Separate Chaining",
      "loadFactor": 0.7,
      "capacity": 20011,
      "itemCount": 14007,
      "searchCount": 28014,
      "insertMedianMs": 4.032599999999547,
      "insertRunsMs": [
        4.789899999999761,
        4.030999999999949,
        4.032599999999547
      ],
      "insertUsPerOp": 0.2878989076889803,
      "searchMedianMs": 5.19800000000032,
      "searchRunsMs": [
        7.343499999999949,
        5.023400000000038,
        5.19800000000032
      ],
      "searchUsPerOp": 0.18555008210181767,
      "found": 14007
    },
    {
      "table": "Linear Probing",
      "loadFactor": 0.7,
      "capacity": 20011,
      "itemCount": 14007,
      "searchCount": 28014,
      "insertMedianMs": 2.5818000000008396,
      "insertRunsMs": [
        9.947400000000016,
        2.5818000000008396,
        2.4989999999997963
      ],
      "insertUsPerOp": 0.1843221246520197,
      "searchMedianMs": 6.221000000000458,
      "searchRunsMs": [
        6.221000000000458,
        6.445800000000418,
        6.1854999999995925
      ],
      "searchUsPerOp": 0.22206753765975792,
      "found": 14007
    },
    {
      "table": "Double Hashing",
      "loadFactor": 0.7,
      "capacity": 20011,
      "itemCount": 14007,
      "searchCount": 28014,
      "insertMedianMs": 3.1177999999999884,
      "insertRunsMs": [
        3.1177999999999884,
        3.3796000000002095,
        3.1066000000000713
      ],
      "insertUsPerOp": 0.2225887056471756,
      "searchMedianMs": 7.105800000000272,
      "searchRunsMs": [
        6.93369999999959,
        7.105800000000272,
        7.5776999999998225
      ],
      "searchUsPerOp": 0.2536517455558032,
      "found": 14007
    },
    {
      "table": "Separate Chaining",
      "loadFactor": 0.8,
      "capacity": 20011,
      "itemCount": 16008,
      "searchCount": 32016,
      "insertMedianMs": 5.673799999999574,
      "insertRunsMs": [
        8.74120000000039,
        4.182800000000498,
        5.673799999999574
      ],
      "insertUsPerOp": 0.35443528235879396,
      "searchMedianMs": 5.975699999999961,
      "searchRunsMs": [
        6.918599999999969,
        5.975699999999961,
        5.877999999999702
      ],
      "searchUsPerOp": 0.1866473013493241,
      "found": 16008
    },
    {
      "table": "Linear Probing",
      "loadFactor": 0.8,
      "capacity": 20011,
      "itemCount": 16008,
      "searchCount": 32016,
      "insertMedianMs": 4.2763999999997395,
      "insertRunsMs": [
        8.798800000000483,
        4.2763999999997395,
        3.5443999999997686
      ],
      "insertUsPerOp": 0.26714142928534107,
      "searchMedianMs": 10.384399999999914,
      "searchRunsMs": [
        10.14089999999942,
        10.384399999999914,
        11.84820000000036
      ],
      "searchUsPerOp": 0.32435032483757853,
      "found": 16008
    },
    {
      "table": "Double Hashing",
      "loadFactor": 0.8,
      "capacity": 20011,
      "itemCount": 16008,
      "searchCount": 32016,
      "insertMedianMs": 4.326500000000124,
      "insertRunsMs": [
        4.389000000000124,
        4.326500000000124,
        4.065399999999499
      ],
      "insertUsPerOp": 0.27027111444278634,
      "searchMedianMs": 8.48449999999957,
      "searchRunsMs": [
        8.48449999999957,
        8.374799999999595,
        8.52770000000055
      ],
      "searchUsPerOp": 0.2650081209395168,
      "found": 16008
    },
    {
      "table": "Separate Chaining",
      "loadFactor": 0.9,
      "capacity": 20011,
      "itemCount": 18009,
      "searchCount": 36018,
      "insertMedianMs": 7.117000000000189,
      "insertRunsMs": [
        7.117000000000189,
        4.982200000000375,
        11.538700000000063
      ],
      "insertUsPerOp": 0.39519129324227825,
      "searchMedianMs": 6.869100000000799,
      "searchRunsMs": [
        8.644900000000234,
        6.869100000000799,
        6.365000000000691
      ],
      "searchUsPerOp": 0.19071297684493305,
      "found": 18009
    },
    {
      "table": "Linear Probing",
      "loadFactor": 0.9,
      "capacity": 20011,
      "itemCount": 18009,
      "searchCount": 36018,
      "insertMedianMs": 5.562699999999495,
      "insertRunsMs": [
        5.562699999999495,
        5.270599999999831,
        9.501199999999699
      ],
      "insertUsPerOp": 0.30888444666552806,
      "searchMedianMs": 26.201000000000022,
      "searchRunsMs": [
        26.201000000000022,
        26.423399999999674,
        26.08979999999974
      ],
      "searchUsPerOp": 0.7274418346382371,
      "found": 18009
    },
    {
      "table": "Double Hashing",
      "loadFactor": 0.9,
      "capacity": 20011,
      "itemCount": 18009,
      "searchCount": 36018,
      "insertMedianMs": 4.6338000000005195,
      "insertRunsMs": [
        4.558999999999287,
        5.11869999999999,
        4.6338000000005195
      ],
      "insertUsPerOp": 0.25730468099286574,
      "searchMedianMs": 12.116799999999785,
      "searchRunsMs": [
        13.536700000000565,
        11.583799999999428,
        12.116799999999785
      ],
      "searchUsPerOp": 0.33640957299127616,
      "found": 18009
    }
  ]
}